netrics/__init__.py
netrics/__main__.py
netrics/cli/include/banner/doom
netrics/conf/include/defaults.yaml
netrics/conf/include/measurements.yaml
netrics/measurement/__init__.py
netrics/measurement/common/__init__.py
netrics/measurement/common/connectivity/__init__.py
netrics/measurement/common/connectivity/command.py
netrics/measurement/common/connectivity/decorator.py
netrics/measurement/common/connectivity/default.py
netrics/measurement/common/connectivity/output.py
netrics/measurement/common/dns.py
netrics/measurement/common/executable.py
netrics/measurement/dev.py
netrics/measurement/dns_latency.py
netrics/measurement/hops.py
netrics/measurement/hops_traceroute.py
netrics/measurement/ip.py
netrics/measurement/lml.py
netrics/measurement/lml_traceroute.py
netrics/measurement/ndt7.py
netrics/measurement/ookla.py
netrics/measurement/ping.py
netrics/sys/platform/include/systemd/netrics.service
netrics/task/__init__.py
netrics/task/param.py
netrics/task/result.py
netrics/task/schema.py
netrics/task/sysexit.py
netrics/util/__init__.py
netrics/util/iterutils.py
netrics/util/lazy_validation.py
netrics/util/procutils.py
netrics_measurements-0.2.0.dist-info/METADATA
netrics_measurements-0.2.0.dist-info/WHEEL
netrics_measurements-0.2.0.dist-info/entry_points.txt
netrics_measurements-0.2.0.dist-info/RECORD
