Metadata-Version: 2.3
Name: netrics-measurements
Version: 0.2.0
Summary: The extensible network measurements framework
License: MIT
Author: Jesse London
Author-email: jesselondon@gmail.com
Requires-Python: >=3.8,<4.0
Classifier: License :: OSI Approved :: MIT License
Classifier: Programming Language :: Python :: 3
Classifier: Programming Language :: Python :: 3.8
Classifier: Programming Language :: Python :: 3.9
Classifier: Programming Language :: Python :: 3.10
Classifier: Programming Language :: Python :: 3.11
Classifier: Programming Language :: Python :: 3.12
Classifier: Programming Language :: Python :: 3.13
Requires-Dist: fate-scheduler (==1.1.0)
Requires-Dist: netifaces (>=0.11.0,<0.12.0)
